vatcompliance/__init__.py
vatcompliance/client.py
vatcompliance-1.0.0.dist-info/LICENSE.txt
vatcompliance-1.0.0.dist-info/METADATA
vatcompliance-1.0.0.dist-info/WHEEL
vatcompliance-1.0.0.dist-info/top_level.txt
vatcompliance-1.0.0.dist-info/RECORD
