Metadata-Version: 2.1
Name: vatcompliance
Version: 1.0.0
Summary: Vatcompliance API client for Python
Home-page: https://vatcompliance.co/
Author: vatcompliance
Author-email: info@vatcompliance.co
License: MIT License
Platform: UNKNOWN
License-File: LICENSE.txt
Requires-Dist: requests (>=2.13.0)
